infinity_embedded/infinity.py
infinity_embedded/errors.py
infinity_embedded/utils.py
infinity_embedded/common.py
infinity_embedded/table.py
infinity_embedded/__init__.py
infinity_embedded/db.py
infinity_embedded/embedded_infinity_ext.abi3.so
infinity_embedded/index.py
infinity_embedded/local_infinity/infinity.py
infinity_embedded/local_infinity/utils.py
infinity_embedded/local_infinity/query_builder.py
infinity_embedded/local_infinity/client.py
infinity_embedded/local_infinity/table.py
infinity_embedded/local_infinity/__init__.py
infinity_embedded/local_infinity/types.py
infinity_embedded/local_infinity/db.py
infinity_embedded_sdk-0.5.2.dist-info/RECORD
infinity_embedded_sdk-0.5.2.dist-info/METADATA
infinity_embedded_sdk-0.5.2.dist-info/WHEEL
infinity_embedded_sdk-0.5.2.dist-info/licenses/LICENSE
