Metadata-Version: 2.1
Name: infinity-embedded-sdk
Version: 0.5.2
Summary: infinity
Requires-Python: >=3.10
Requires-Dist: sqlglot~=11.7.0
Requires-Dist: pydantic~=2.9.0
Requires-Dist: thrift~=0.20.0
Requires-Dist: setuptools~=75.2.0
Requires-Dist: pytest~=8.3.0
Requires-Dist: pandas~=2.2.0
Requires-Dist: numpy~=1.26.0
Requires-Dist: pyarrow~=17.0.0
Requires-Dist: polars~=1.9.0
Requires-Dist: openpyxl~=3.1.0
Requires-Dist: requests~=2.32.0
